parsik/__init__.py
parsik/logutils.py
parsik/matchers.py
parsik/parser.py
parsik/parsik.py
parsik-0.9.3.dist-info/LICENSE
parsik-0.9.3.dist-info/METADATA
parsik-0.9.3.dist-info/WHEEL
parsik-0.9.3.dist-info/top_level.txt
parsik-0.9.3.dist-info/RECORD
