Metadata-Version: 2.1
Name: parsik
Version: 0.9.3
Summary: A minimalistic PEG parser
Home-page: https://github.com/nfomon/parsik
Author: Mike Biggs
Author-email: nfomon@users.noreply.github.com
License: UNKNOWN
Keywords: parser,parsing-library,peg
Platform: UNKNOWN
Classifier: Programming Language :: Python :: 3
Classifier: License :: OSI Approved :: GNU General Public License v3 (GPLv3)
Classifier: Operating System :: OS Independent
